cocotb_tools/runner.py
cocotb_tools/config.py
cocotb_tools/_coverage.py
cocotb_tools/__init__.py
cocotb_tools/combine_results.py
cocotb_tools/check_results.py
cocotb_tools/ipython_support.py
cocotb_tools/py.typed
cocotb_tools/sim_versions.py
cocotb_tools/_vendor/__init__.py
cocotb_tools/_vendor/distutils_version.py
cocotb_tools/makefiles/Makefile.deprecations
cocotb_tools/makefiles/Makefile.sim
cocotb_tools/makefiles/Makefile.inc
cocotb_tools/makefiles/simulators/Makefile.ius
cocotb_tools/makefiles/simulators/Makefile.modelsim
cocotb_tools/makefiles/simulators/Makefile.activehdl
cocotb_tools/makefiles/simulators/Makefile.vcs
cocotb_tools/makefiles/simulators/Makefile.ghdl
cocotb_tools/makefiles/simulators/Makefile.questa-compat
cocotb_tools/makefiles/simulators/Makefile.xcelium
cocotb_tools/makefiles/simulators/Makefile.cvc
cocotb_tools/makefiles/simulators/Makefile.verilator
cocotb_tools/makefiles/simulators/Makefile.questa-qisqrun
cocotb_tools/makefiles/simulators/Makefile.riviera
cocotb_tools/makefiles/simulators/Makefile.dsim
cocotb_tools/makefiles/simulators/Makefile.nvc
cocotb_tools/makefiles/simulators/Makefile.icarus
cocotb_tools/makefiles/simulators/Makefile.questa
pygpi/__init__.py
pygpi/entry.py
pygpi/py.typed
cocotb-2.0.1.dist-info/RECORD
cocotb-2.0.1.dist-info/LICENSE
cocotb-2.0.1.dist-info/WHEEL
cocotb-2.0.1.dist-info/entry_points.txt
cocotb-2.0.1.dist-info/top_level.txt
cocotb-2.0.1.dist-info/METADATA
cocotb/queue.py
cocotb/logging.py
cocotb/task.py
cocotb/regression.py
cocotb/_ANSI.py
cocotb/_typing.py
cocotb/triggers.py
cocotb/_init.py
cocotb/_version.py
cocotb/handle.py
cocotb/simulator.cpython-38-darwin.so
cocotb/simulator.pyi
cocotb/_deprecation.py
cocotb/clock.py
cocotb/_py_compat.py
cocotb/_extended_awaitables.py
cocotb/__init__.py
cocotb/_test_functions.py
cocotb/result.py
cocotb/_test.py
cocotb/_scheduler.py
cocotb/_bridge.py
cocotb/utils.py
cocotb/_decorators.py
cocotb/_profiling.py
cocotb/debug.py
cocotb/_gpi_triggers.py
cocotb/_outcomes.py
cocotb/py.typed
cocotb/simtime.py
cocotb/_base_triggers.py
cocotb/_xunit_reporter.py
cocotb/_exceptions.py
cocotb/_test_factory.py
