Metadata-Version: 2.1
Name: cocotb
Version: 2.0.1
Summary: cocotb is a coroutine based cosimulation library for writing VHDL and Verilog testbenches in Python.
Home-page: https://www.cocotb.org
Author: Chris Higgs, Stuart Hodgson
Maintainer: cocotb contributors
Maintainer-email: cocotb@lists.librecores.org
License: BSD-3-Clause
Project-URL: Bug Tracker, https://github.com/cocotb/cocotb/issues
Project-URL: Source Code, https://github.com/cocotb/cocotb
Project-URL: Documentation, https://docs.cocotb.org
Platform: any
Classifier: Programming Language :: Python :: 3
Classifier: Programming Language :: Python :: 3.6
Classifier: Programming Language :: Python :: 3.7
Classifier: Programming Language :: Python :: 3.8
Classifier: Programming Language :: Python :: 3.9
Classifier: Programming Language :: Python :: 3.10
Classifier: Programming Language :: Python :: 3.11
Classifier: Programming Language :: Python :: 3.12
Classifier: Programming Language :: Python :: 3.13
Classifier: Topic :: Scientific/Engineering :: Electronic Design Automation (EDA)
Classifier: Framework :: cocotb
Requires-Python: >=3.6.2
License-File: LICENSE
Requires-Dist: find-libpython
